pybtpanel/__init__.py
pybtpanel-1.1.dist-info/LICENSE
pybtpanel-1.1.dist-info/METADATA
pybtpanel-1.1.dist-info/WHEEL
pybtpanel-1.1.dist-info/top_level.txt
pybtpanel-1.1.dist-info/RECORD
