Metadata-Version: 2.2
Name: pybtpanel
Version: 1.1
Summary: 一个宝塔面板api的包
Home-page: https://github.com/zzqfbzz/pybtpanel
Author: zzqfbzz
Classifier: Programming Language :: Python :: 3
Classifier: Operating System :: Unix
Classifier: Operating System :: MacOS :: MacOS X
Classifier: Operating System :: Microsoft :: Windows
License-File: LICENSE
Requires-Dist: requests
Dynamic: author
Dynamic: classifier
Dynamic: description
Dynamic: description-content-type
Dynamic: home-page
Dynamic: requires-dist
Dynamic: summary
